HISTORY.md
MANIFEST.in
README.md
setup.py
btc_top_pool_api_sdk/__init__.py
btc_top_pool_api_sdk.egg-info/PKG-INFO
btc_top_pool_api_sdk.egg-info/SOURCES.txt
btc_top_pool_api_sdk.egg-info/dependency_links.txt
btc_top_pool_api_sdk.egg-info/not-zip-safe
btc_top_pool_api_sdk.egg-info/requires.txt
btc_top_pool_api_sdk.egg-info/top_level.txt