Metadata-Version: 2.1
Name: btc-top-pool-api-sdk
Version: 1.0.2
Summary: Pool OpenAPI SDK.
Home-page: https://github.com/btc-top/pool-api-doc
Author: Mars Yuan
Author-email: marshalys@gmail.com
License: UNKNOWN
Keywords: pool-api-sdk
Platform: UNKNOWN
Classifier: Programming Language :: Python :: 3
